[
    {"lat": 19.4326, "lng": -99.1332},
    {"lat": 19.4352, "lng": -99.1412},
    {"lat": 19.4270, "lng": -99.1677},
    {"lat": 19.4205, "lng": -99.1818},
    {"lat": 19.4260, "lng": -99.1862},
    {"lat": 19.4846, "lng": -99.1173},
    {"lat": 19.4407, "lng": -99.2047},
    {"lat": 19.3551, "lng": -99.1625},
    {"lat": 19.3484, "lng": -99.1608},
    {"lat": 19.2838, "lng": -99.1031},
    {"lat": 19.4172, "lng": -99.1622},
    {"lat": 19.4150, "lng": -99.1718},
    {"lat": 19.3626, "lng": -99.2310},
    {"lat": 19.3323, "lng": -99.1882},
    {"lat": 19.3248, "lng": -99.1810},
    {"lat": 19.4200, "lng": -99.1415},
    {"lat": 19.4360, "lng": -99.1550},
    {"lat": 19.3907, "lng": -99.1744},
    {"lat": 19.4332, "lng": -99.1451},
    {"lat": 19.4426, "lng": -99.1475}
  ]